{
  "_generated": true,
  "_doNotEdit": "GENERATED from canonical FitShield data (blocklists/*.json) via the separated engine (blocklist.js). Run `npm run generate:android` to regenerate. Do NOT hand-edit — tools/android-audit.js fails the build on drift.",
  "schema": 1,
  "engine": "blocklist.js",
  "source": [
    "blocklists/fast-food.json",
    "blocklists/delivery.json"
  ],
  "datasetVersions": {
    "fast-food": "1.1",
    "delivery": "1.1"
  },
  "appVersion": "0.52",
  "matching": "apex-or-subdomain",
  "count": 2585,
  "sha256": "9cc3f8074aa7a3e4233ac03bcac3c129b97fd02a729e01a926f101a117e9ce81",
  "hosts": [
    "100montaditos.com",
    "1112.com",
    "12hotpot.com.tw",
    "1441pizzeria.com",
    "1d1d.com.cn",
    "21cake.com",
    "241pizza.com",
    "2berega.ru",
    "49thcoffee.com",
    "50lan.com",
    "551horai.co.jp",
    "58.com",
    "58daojia.com",
    "60chicken.com",
    "7-11.com.tw",
    "7-eleven.com.ph",
    "7-eleven.vn",
    "759store.com",
    "7brau.com",
    "7brew.com",
    "7eleven.com.au",
    "7eleven.se",
    "85cafe.com",
    "85cafe.com.tw",
    "99food.com.br",
    "a2brestaurant.com",
    "aabsweets.com",
    "abaty.com",
    "abbyspizza.com",
    "abcoffee.co",
    "absolutebarbecues.com",
    "abuelos.com",
    "acapulcos.net",
    "africabites.com",
    "afrimarket.fr",
    "afteryoudessertcafe.com",
    "afuri.com",
    "agrawalsweets.com",
    "ah.nl",
    "ahodrink.com",
    "aiqfome.com",
    "aiqfome.com.br",
    "airasiafood.com",
    "ajino-mingei.co.jp",
    "ajisen.com.cn",
    "ajisen.com.hk",
    "akhbarelyomfood.com",
    "akiyab.com",
    "aklyakl.com",
    "aladdins.com",
    "albaikfoods.in",
    "albertos.net",
    "albertosmexicanfood.com",
    "alcampo.es",
    "aldi-nord.de",
    "aldi-sued.de",
    "aldi.co.uk",
    "aldi.com.au",
    "alicepizza.it",
    "allbarone.co.uk",
    "allsetnow.com",
    "allstarpizza.com",
    "alohasalads.com",
    "amatos.com",
    "ambassador.ai",
    "americandeli.com",
    "americansteakburger.com",
    "amrest.eu",
    "amul.com",
    "andpizza.com",
    "angelina-paris.fr",
    "angelinaspizza.com",
    "angelinus.com",
    "angelinuscoffee.com",
    "angelos.com",
    "anjappar.com",
    "annas.com",
    "anomali.coffee",
    "anota.ai",
    "anotherbrokeneggcafe.com",
    "anotherhoundcafe.com",
    "anrakutei.co.jp",
    "aokispizza.co.jp",
    "appetito24.com",
    "appetito24.com.do",
    "appetito24.com.pa",
    "applebees.com",
    "applebees.com.br",
    "arbuz.kz",
    "arbys.com",
    "archies.co",
    "arclandservice.co.jp",
    "aristocrat.com.ph",
    "armandospizza.com",
    "arnolds.fi",
    "artcaffe.com",
    "artigiano.com",
    "asap.com",
    "asap.com.jm",
    "asapdelivery.com",
    "asapdelivery.com.tt",
    "asda.com",
    "ashley.co.kr",
    "asianbox.com",
    "asianchao.com",
    "askitalian.co.uk",
    "assai.com.br",
    "atacadao.com.br",
    "atlantabread.com",
    "atom-corp.co.jp",
    "aubonpain.com",
    "auchan.be",
    "auchan.fr",
    "auchan.lu",
    "auchan.pl",
    "auchan.pt",
    "aunteajenny.us",
    "auntieannes.com",
    "autogrill.it",
    "awrestaurants.com",
    "ayamgeprekjuara.com",
    "ayamgorengsuharti.com",
    "baanying.com",
    "bachhoaxanh.com",
    "backfactory.de",
    "backwerk.de",
    "backyardburger.com",
    "backyardburgers.com",
    "badasscoffee.com",
    "badmamas.com",
    "baekjeong.com",
    "baemin.co.kr",
    "baemin.com",
    "baemin.me",
    "baemin.vn",
    "bagelboss.com",
    "bagelfactory.co.uk",
    "bagelsandbeans.nl",
    "bagelsbeans.nl",
    "bagelworks.com",
    "baiduwaimai.com",
    "bajfood.com",
    "bakersdrivethru.com",
    "bakkerbart.nl",
    "bakmigm.com",
    "baleadasexpress.com",
    "balzac-coffee.com",
    "balzacs.com",
    "bandanabbq.com",
    "banu.cn",
    "barbequenation.com",
    "barberitos.com",
    "barbora.lt",
    "barbora.lv",
    "barburrito.ca",
    "barburrito.co.uk",
    "bargainbox.co.nz",
    "barista.com.tw",
    "barrospizza.com",
    "barrysbagels.com",
    "basefood.co.jp",
    "baskinrobbins.ca",
    "baskinrobbins.co.kr",
    "baskinrobbins.com",
    "baskinrobbinsindia.com",
    "bastardburgers.com",
    "batonrouge.ca",
    "bauducco.com.br",
    "bawarchi.com",
    "bawarchibiryani.com",
    "bbq.co.kr",
    "bbqchicken.com",
    "bbqmall.co.kr",
    "bbqnation.com",
    "bbqplaza.com",
    "beachhutdeli.com",
    "beand.cn",
    "beardpapa.com.cn",
    "beardpapa.jp",
    "beardpapas.com",
    "beardpapas.com.tw",
    "beavertails.com",
    "bebekkaleyo.com",
    "becksprime.com",
    "beefaroo.com",
    "beefobradys.com",
    "beepit.com.ph",
    "befood.vn",
    "behrouzbiryani.com",
    "belgianwaffle.co",
    "bellacinos.com",
    "benihana.com",
    "benssoftpretzels.com",
    "bentoya.jp",
    "bertuccis.com",
    "best-inc.com",
    "bettysburgers.com.au",
    "beyondmenu.com",
    "bhc.co.kr",
    "bhcchicken.global",
    "bhcgroup.co.kr",
    "bibibop.com",
    "biedronka.pl",
    "biermarkt.com",
    "bifengtang.com.cn",
    "bigchicken.com",
    "bigfernand.com",
    "biggby.com",
    "biggiesburger.com",
    "bikanervala.com",
    "bikano.com",
    "bikkuri-donkey.com",
    "bilka.dk",
    "billmillersbbq.com",
    "biryaniblues.com",
    "biryanibykilo.com",
    "biryanihouse.in",
    "biryanipot.com",
    "biryaniwala.com",
    "biryanizone.com",
    "biscuithead.com",
    "biscuitville.com",
    "bitesquad.com",
    "bk.com",
    "blackbeardiner.com",
    "blackcanyoncoffee.com",
    "blacksheepcoffee.co.uk",
    "blankstreet.com",
    "blazepizza.com",
    "blazinsteaks.com",
    "blenz.com",
    "blimpie.com",
    "blucabana.com",
    "bluebottlecoffee.jp",
    "bluetokaicoffee.com",
    "boardandbrew.com",
    "bobs.com.br",
    "bojangles.com",
    "bolay.com",
    "bolt.eu",
    "boltfood.com",
    "boltfood.cz",
    "boltfood.ee",
    "boltfood.fi",
    "boltfood.gh",
    "boltfood.hr",
    "boltfood.hu",
    "boltfood.lt",
    "boltfood.lv",
    "boltfood.ng",
    "boltfood.pl",
    "boltfood.pt",
    "boltfood.ro",
    "boltfood.si",
    "boltfood.sk",
    "boncake.com",
    "bonchon.com",
    "bones.dk",
    "bonfresh.com",
    "bonif.co.kr",
    "bonjuk.co.kr",
    "boosterjuice.com",
    "boostjuice.co.nz",
    "boostjuice.com.au",
    "booths.co.uk",
    "bornga.co.kr",
    "bornga.com",
    "boscoffee.com",
    "bossburger.in",
    "bostonpizza.com",
    "botejyu.co.jp",
    "bottlesapp.co.za",
    "bottomless.com",
    "bourbonstgrill.com",
    "box8.in",
    "braveroasters.com",
    "bravissimo.cl",
    "bravospizza.com",
    "bread-espresso.jp",
    "breadfast.com",
    "breadtalk.com",
    "breadtalk.com.cn",
    "breadtalkthailand.com",
    "brewstersicecream.com",
    "brgrmeister.com",
    "bridgehead.ca",
    "bringo.uz",
    "briochedoree.fr",
    "brodernas.nu",
    "bronco.co.jp",
    "broniboy.ru",
    "brooklynroasting.jp",
    "brownbagseafood.com",
    "browniesanddownies.nl",
    "browns-restaurants.co.uk",
    "brueggers.com",
    "bubbakoos.com",
    "bubbakoosburritos.com",
    "buffalowildwings.com",
    "bukkahut.com",
    "bullguer.com",
    "burger21.com",
    "burgerfarm.in",
    "burgerfi.com",
    "burgerfuel.com",
    "burgerim.com",
    "burgerista.com",
    "burgerking.cl",
    "burgerking.co.jp",
    "burgerking.co.kr",
    "burgerking.co.nz",
    "burgerking.co.uk",
    "burgerking.com",
    "burgerking.com.br",
    "burgerking.com.cn",
    "burgerking.com.hk",
    "burgerking.com.ph",
    "burgerking.com.sg",
    "burgerking.com.tw",
    "burgerking.in",
    "burgerking.ke",
    "burgerking.ma",
    "burgerking.pl",
    "burgerking.vn",
    "burgerkingthailand.com",
    "burgerlab.com.br",
    "burgerlounge.com",
    "burgerme.de",
    "burgermonger.com",
    "burgerray.com",
    "burgerseigneur.com",
    "burgershack.com",
    "burgersingh.com",
    "burgersinghonline.com",
    "burgerurge.com.au",
    "burgerville.com",
    "burgrill.in",
    "burritobeach.com",
    "burritoparrilla.com",
    "butterburgers.com",
    "c-united.co.jp",
    "cacaushow.com.br",
    "cactusclubcafe.com",
    "cafe3coracoes.com.br",
    "cafecoffeeday.com",
    "cafedecoral.com",
    "cafedecoral.com.hk",
    "cafejavas.com",
    "cafejoyeux.com",
    "cafemartinez.com",
    "cafeneo.com",
    "caferio.com",
    "cafeyumm.com",
    "cafezupas.com",
    "caffebene.com",
    "caffenero.com",
    "cainiao.com",
    "cainiao.com.cn",
    "califchickencafe.com",
    "californiaburrito.com",
    "californiaburrito.in",
    "californiapizzakitchen.com",
    "californiatortilla.com",
    "call-a-pizza.de",
    "cama.cafe",
    "campero.com",
    "cannolis.com",
    "cantinalaredo.com",
    "capichiapp.com",
    "caprabo.com",
    "capriottis.com",
    "captainds.com",
    "captaintoms.com",
    "careem.com",
    "careemfood.com",
    "cariboucoffee.com",
    "carls.com",
    "carlsjr.com",
    "carrefour.be",
    "carrefour.ci",
    "carrefour.com.br",
    "carrefour.com.tw",
    "carrefour.es",
    "carrefour.fr",
    "carrefour.it",
    "carrefour.ke",
    "carrefour.ma",
    "carrefour.pl",
    "carriage.com.my",
    "carulla.com",
    "carvel.com",
    "casabauducco.com.br",
    "casadeltaco.com",
    "casadopao.com.br",
    "casperandgambinis.com",
    "catchtable.co.kr",
    "caviar.com",
    "cbtl.com.ph",
    "centralgroup.com",
    "cfcindonesia.com",
    "chaayos.com",
    "chabaidao.com",
    "chabuton.com",
    "chachas.com",
    "chagee.com",
    "chaibunk.com",
    "chaicraft.com",
    "chaikings.com",
    "chaipoint.com",
    "chaisuttabarindia.com",
    "chaiwaale.com",
    "chamate.cn",
    "champachicken.com",
    "chargrill.com",
    "chargrillcharlies.com.au",
    "charleys.com",
    "charleyscheesesteaks.com",
    "charleysphillysteaks.com",
    "chateraise.co.jp",
    "chatime.com",
    "chatime.com.au",
    "chatime.com.ph",
    "chatime.com.tw",
    "chayan.com",
    "chebahut.com",
    "checkers.com",
    "checkers60.com",
    "cheddars.com",
    "cheeburger.com",
    "cheeseburgerbobbys.com",
    "cheesecakefactory.com",
    "cheesecakelabs.com",
    "cheesiano.com",
    "cheesiano.in",
    "chefexpress.it",
    "chefgood.com.au",
    "cheiljemyunso.co.kr",
    "cheirinbao.com.br",
    "cheogajip.co.kr",
    "chesterfriedchicken.com",
    "chevys.com",
    "chibbis.ru",
    "chibo.com",
    "chibuku.com",
    "chicagopizza.jp",
    "chick-fil-a.com",
    "chickenexpress.com",
    "chickenfillet.com",
    "chickenkitchen.com",
    "chickenplus.co.kr",
    "chilis.com",
    "chilis.com.tw",
    "chimney.co.jp",
    "chipotle.com",
    "chiquinho.com.br",
    "chirchir.co.kr",
    "chirchir.com",
    "chlopskiejadlo.pl",
    "chocofood.kz",
    "chope.co",
    "chopstixnoodles.co.uk",
    "chopstop.com",
    "chowcentral.com",
    "chowdeck.com",
    "chowking.com",
    "chownow.com",
    "chronictacos.com",
    "chunshuitang.com.tw",
    "churchs.com",
    "cigierre.com",
    "cilantrocafe.com",
    "cinnabon.com",
    "citybbq.com",
    "citybirds.com",
    "citycafe.com.tw",
    "citygross.se",
    "cjfoodville.com",
    "cjscafe.com",
    "claimjumper.com",
    "cleanjuice.com",
    "clickandfood.fr",
    "cloverfoodlab.com",
    "clubharie.jp",
    "clustertruck.com",
    "cmchicken.com",
    "cnhls.com",
    "co-opdeli.jp",
    "cobsbread.com",
    "coca.com",
    "coco-tea.com",
    "cocobambu.com",
    "cocobubbletea.com",
    "cocosbakery.com",
    "cocottes.lu",
    "coffee-fellows.com",
    "coffeebay.com",
    "coffeebean.com",
    "coffeebeanery.com",
    "coffeebeankorea.com",
    "coffeecompany.nl",
    "coffeeculturecafe.com",
    "coffeefellows.com",
    "coffeerepublic.co.uk",
    "coffeerepublic.com",
    "coffine.co.kr",
    "cofix.global",
    "cofix.ru",
    "coldbeersandcheeseburgers.com",
    "coldstonecreamery.com",
    "coldstonecreamery.ng",
    "coldstorage.com.sg",
    "coles.com.au",
    "colonygrill.com",
    "colowide.co.jp",
    "colruyt.be",
    "columbuscafe.com",
    "com.ao",
    "com.ls",
    "comebuy2002.com.tw",
    "comebuytea.com",
    "composecoffee.com",
    "conad.it",
    "condadotacos.com",
    "congcaphe.com",
    "continente.pt",
    "contis.ph",
    "cookfood.net",
    "cookout.com",
    "cookpad.com.cn",
    "cookshack.com",
    "coop.co.uk",
    "coop.dk",
    "coop.it",
    "coop.no",
    "coop.se",
    "coopershawk.com",
    "coopmart.vn",
    "copperbranch.com",
    "cornerbakerycafe.com",
    "costa.co.uk",
    "costa.coffee",
    "costa.pl",
    "costco.com.tw",
    "cosyclub.co.uk",
    "cote.co.uk",
    "cotijas.com",
    "cotti.com",
    "cotticoffee.com",
    "cottonpatch.com",
    "countdown.co.nz",
    "countrystyle.com",
    "countrystylecooking.com",
    "coupang.com",
    "coupangeats.com",
    "courtepaille.com",
    "cousinsmainelobster.com",
    "cousinssubs.com",
    "cpk.com",
    "craftpizza.com",
    "creambell.com",
    "creamsgelato.com",
    "creamyboys.com",
    "create-restaurants.co.jp",
    "crepesywaffles.com",
    "crepevine.com",
    "crispers.com",
    "crisppizza.com",
    "croasonho.com.br",
    "crust.com.au",
    "csc100.com",
    "cult.fit",
    "culturesrestaurants.com",
    "culvers.com",
    "cupbop.com",
    "currito.com",
    "dada.cn",
    "dadajiasong.com",
    "dagrasso.pl",
    "daichi-m.co.jp",
    "dailygrill.com",
    "dairykeen.com",
    "dairyqueen.ca",
    "dairyqueen.com.cn",
    "dalkomm.com",
    "dalongyi.com",
    "dangelos.com",
    "danggeunmarket.com",
    "daojia.com",
    "daojia.jd.com",
    "daoxiangcun.com",
    "darumataishi.com",
    "dashdelivery.co.za",
    "dayungs.com.tw",
    "dd-holdings.jp",
    "ddangddang.co.kr",
    "ddangyo.com",
    "deananddavid.com",
    "debakkerswinkel.nl",
    "delhaize.be",
    "delhaize.lu",
    "deliaschicken.com",
    "delitraiteur.com",
    "delivereasy.co.nz",
    "delivereat.my",
    "deliveroo.ae",
    "deliveroo.be",
    "deliveroo.co.uk",
    "deliveroo.com.sg",
    "deliveroo.es",
    "deliveroo.fr",
    "deliveroo.hk",
    "deliveroo.ie",
    "deliveroo.it",
    "delivery-club.ru",
    "delivery.com",
    "deliverydireto.com.br",
    "deliverydudes.com",
    "deliveryk.com",
    "deliverymuch.com.br",
    "deliveryvip.com.br",
    "delivroum.com",
    "deltaco.com",
    "deltacos.com",
    "demae-can.com",
    "demaecan.com",
    "dennys.ca",
    "denverbiscuitco.com",
    "deppon.com",
    "dezh.com",
    "dezhuang.com",
    "dial-a-delivery.co.ke",
    "dial-a-meal.co.zw",
    "dianping.com",
    "dickeys.com",
    "dicos.com.cn",
    "didi-food.cl",
    "didi-food.com",
    "didi-food.com.br",
    "didi-food.com.co",
    "didi-food.com.mx",
    "didi-food.cr",
    "didi-food.pe",
    "dietician.jp",
    "dinnerly.com.au",
    "dintaifung.com.tw",
    "ditsch.de",
    "dixiecream.com",
    "dodo.ru",
    "doggis.cl",
    "doghaus.com",
    "doghausbiergarten.com",
    "domdom.jp",
    "domdomhamburger.com",
    "dominos.ca",
    "dominos.co.kr",
    "dominos.co.nz",
    "dominos.co.uk",
    "dominos.com",
    "dominos.com.au",
    "dominos.com.br",
    "dominos.com.cn",
    "dominos.com.ph",
    "dominos.com.sg",
    "dominos.com.tw",
    "dominos.jp",
    "dominos.ma",
    "dominos.ng",
    "dominos.nl",
    "dominos.vn",
    "dominospizza.cl",
    "don-tei.jp",
    "donatospizza.com",
    "donglaishun.com",
    "donq.co.jp",
    "donutes.com.tw",
    "donutking.com.au",
    "dookki.co.kr",
    "doordash.com",
    "dosaplaza.com",
    "dosbros.com",
    "dosirak.com",
    "dostaevsky.ru",
    "douguo.com",
    "dq.com",
    "dqchina.com",
    "dqxg.com",
    "dqy.com.cn",
    "dreamerscoffee.com.tw",
    "droptop.co.kr",
    "drunkenmonkey.co",
    "druther.com",
    "drvegefru.com",
    "dunkin.co.uk",
    "dunkindonuts.co.kr",
    "dunkindonuts.com",
    "dunkinindia.com",
    "duyichu.com",
    "dzg.com.cn",
    "e.leclerc",
    "ea.com",
    "each-a-cup.com",
    "eagleboys.com.au",
    "earls.ca",
    "easi.com.au",
    "eastofchicago.com",
    "eastsidemarios.com",
    "eatclub.com.au",
    "eatclub.in",
    "eatdrinkkl.com",
    "eateasily.co.zw",
    "eatfit.in",
    "eatfitgo.com",
    "eatigo.com",
    "eatigo.hk",
    "eatigo.my",
    "eatigo.ph",
    "eatigo.sg",
    "eatigo.th",
    "eatigo.vn",
    "eatnpark.com",
    "eatogether.com.tw",
    "eatstreet.com",
    "eatsure.com",
    "eazie.nl",
    "eazzyeats.com",
    "eda.yandex.ru",
    "edeka.de",
    "ediya.com",
    "eegees.com",
    "eggdrop.co.kr",
    "eggslut.com",
    "eggsmart.com",
    "egon.no",
    "einsteinbros.com",
    "elclubdelamilanesa.com",
    "elcorral.com",
    "ele.me",
    "eleme.cn",
    "eleme.hk",
    "ellis.be",
    "elmenus.com",
    "elmeson.com",
    "elpolloloco.com",
    "eltorito.com",
    "emberinns.co.uk",
    "emmerys.dk",
    "emoi.co.kr",
    "empanadaloca.com",
    "emporiolarosa.cl",
    "epicburger.com",
    "epizza.pl",
    "eroski.es",
    "erospizza.com",
    "espressohouse.com",
    "esquirescoffee.co.nz",
    "esselunga.it",
    "eurekaburger.com",
    "everbowl.com",
    "everyplate.com.au",
    "evos.com",
    "excelsiorcafe.com",
    "excelso-coffee.com",
    "exito.com",
    "exki.com",
    "express24.kg",
    "express24.uz",
    "extremepita.com",
    "ezcater.com",
    "faasos.com",
    "faasos.io",
    "fairprice.com.sg",
    "fairwood.com.hk",
    "family.com.tw",
    "familyset.jp",
    "fanfoodapp.com",
    "fantuan.ca",
    "fantuan.com",
    "farfor.ru",
    "farmerboys.com",
    "farmerboysfood.com",
    "farrellsusa.com",
    "fatbastardburrito.ca",
    "fatburger.com",
    "fatshack.com",
    "favor.com",
    "fazolis.com",
    "feastfood.co.ke",
    "febo.nl",
    "fengniao.com",
    "fengniaodelivery.com",
    "fengniaozhongbao.cn",
    "fielderschoiceicecream.com",
    "fieldscoffee.com",
    "figaro.ph",
    "figaros.com",
    "filibertos.com",
    "fine-dine.jp",
    "firangibake.com",
    "firebirdsrestaurants.com",
    "firehousesubs.com",
    "firewings.com",
    "firezza.com",
    "first-kitchen.co.jp",
    "fishandchick.com",
    "fishwindow.com",
    "fitfoodhome.jp",
    "fiveguys.co.uk",
    "fiveguys.com",
    "flamebroiler.com",
    "flanigans.net",
    "flashcoffee.com",
    "flashex.com",
    "flashhold.com",
    "flipdish.com",
    "flipperspizza.com",
    "flippinpizza.com",
    "flunch.fr",
    "flurys.com",
    "flyingbiscuit.com",
    "foetex.dk",
    "food-kr.com",
    "food.grab.com",
    "food.jumia.com",
    "foodbomb.com.au",
    "foodbooking.com",
    "foodcourt.app",
    "foodee.co.za",
    "foodfly.co.kr",
    "foodgate.net",
    "foodhwy.com",
    "foodi.com.bd",
    "foodies.co.za",
    "foodmaker.be",
    "foodonline.co.za",
    "foodora.at",
    "foodora.bg",
    "foodora.ca",
    "foodora.com",
    "foodora.cz",
    "foodora.dk",
    "foodora.fi",
    "foodora.hu",
    "foodora.no",
    "foodora.ro",
    "foodora.se",
    "foodpanda.bd",
    "foodpanda.bg",
    "foodpanda.com",
    "foodpanda.hk",
    "foodpanda.jp",
    "foodpanda.kh",
    "foodpanda.la",
    "foodpanda.my",
    "foodpanda.ph",
    "foodpanda.pk",
    "foodpanda.ro",
    "foodpanda.sg",
    "foodpanda.sk",
    "foodpanda.tw",
    "foodpanda.vn",
    "foodprint.co.nz",
    "foodrepublic.com.sg",
    "foodscene.delivery",
    "foodstantly.com",
    "foody.com.co",
    "foody.com.cy",
    "foody.com.mx",
    "foody.vn",
    "foosacklys.net",
    "fore.coffee",
    "fornetti.com",
    "fosterhollywood.es",
    "fostersfreeze.com",
    "foursquare.co.nz",
    "frankie.in",
    "franprix.fr",
    "frasses.se",
    "freddys.com",
    "freddysfrozencustard.com",
    "freshbrothers.com",
    "freshii.com",
    "freshlysqueezed.ca",
    "freshmenu.com",
    "freshnessburger.co.jp",
    "freshpressery.com",
    "freshslice.com",
    "freshtoorder.com",
    "friendlystop.com",
    "friendsandbrgrs.fi",
    "frischs.com",
    "frittenwerk.com",
    "frozencustard.com",
    "fuddruckers.com",
    "fugetsu.jp",
    "fujisoba.co.jp",
    "fujiya-peko.co.jp",
    "fuku.com",
    "fukuintown.com",
    "fukutaro.co.jp",
    "furaibo.com",
    "fusionpoke.com",
    "fuunji.com",
    "fuyujia.com",
    "fuzzystacoshop.com",
    "gabrielpizza.com",
    "gailsbread.co.uk",
    "galitos.com",
    "gandolfosdeli.com",
    "ganji.com",
    "ganso.com.cn",
    "gar.com",
    "garbanzomediterraneanfresh.com",
    "gatten.co.jp",
    "gbk.co.uk",
    "gelatissimo.com.au",
    "gendai.com.br",
    "genesisbbq.co.kr",
    "genkisushi.co.jp",
    "genkisushi.com.sg",
    "georges.com",
    "georgesgreekcafe.com",
    "gianiicecream.com",
    "giant.sg",
    "gigi-coffee.com",
    "giguo.com.tw",
    "gimbapheaven.co.kr",
    "gindaco.com",
    "ginnoan.com",
    "ginos.es",
    "ginza-renoir.co.jp",
    "ginza-west.com",
    "gioninos.com",
    "giordanos.com",
    "giraffas.com.br",
    "giraffe.net",
    "global-dining.com",
    "gloriajeans.com.au",
    "gloriasrestaurants.com",
    "glorydaysgrill.com",
    "glovo.ba",
    "glovo.ci",
    "glovo.com",
    "glovo.es",
    "glovo.gh",
    "glovo.hr",
    "glovo.it",
    "glovo.ke",
    "glovo.kz",
    "glovo.ma",
    "glovo.md",
    "glovo.ng",
    "glovo.pl",
    "glovo.pt",
    "glovo.ro",
    "glovo.rs",
    "glovo.si",
    "glovo.tn",
    "glovo.ug",
    "glovoapp.com",
    "go-vietnam.vn",
    "gochickengo.com",
    "gochikuru.com",
    "godfathers.com",
    "gofood.co.id",
    "gogocurry.com",
    "gojek.com",
    "gokada.ng",
    "goldbelly.com",
    "goldenchick.com",
    "goldilocks.com.ph",
    "goldstarchili.com",
    "golivadapav.com",
    "gong-cha.co.kr",
    "gong-cha.com",
    "gong-cha.com.tw",
    "gong-cha.kr",
    "gongcha.ca",
    "gongcha.co.nz",
    "gongcha.com.au",
    "gongcha.com.ph",
    "gongcha.com.sg",
    "gongcha.com.tw",
    "goobne.co.kr",
    "goodberrys.com",
    "goodcentssubs.com",
    "goodflippin.com",
    "goodtimesburgers.com",
    "goomer.com.br",
    "gopizza.com",
    "gopizza.in",
    "gopizza.kr",
    "gorillas.io",
    "goshuttle.com",
    "goubuli.com",
    "gourmetburgerkitchen.com",
    "gourmetmarketthailand.com",
    "gozem.co",
    "grab.com",
    "grabfood.com",
    "grabli.ru",
    "greatsteak.com",
    "greatwraps.com",
    "greco.ca",
    "greeks.com",
    "greekxpress.com",
    "green-spoon.jp",
    "greenking.com.cn",
    "greenwich.com.ph",
    "greggs.co.uk",
    "greyboxcoffee.com",
    "gridohelado.com",
    "griletto.com.br",
    "grilld.com.au",
    "grimaldispizzeria.com",
    "grindhouseburgers.com",
    "gringos.com",
    "groundround.com",
    "grubhub.com",
    "gudumami.com",
    "gumingnc.com",
    "gusfriedchicken.com",
    "guzmanygomez.com",
    "gyuan.co.jp",
    "gyukaku.ne.jp",
    "h3.com",
    "h5.ele.me",
    "habibs.com.br",
    "habitburger.com",
    "habitburgergrill.com",
    "hachiban.jp",
    "haema.de",
    "haidilao.com",
    "haldiram.com",
    "haloburger.com",
    "hamakatsu.jp",
    "hanamaruken.com",
    "hanamaruudon.com",
    "hananomai.co.jp",
    "hanbey.com",
    "hanshinpocha.com",
    "hansot.co.kr",
    "hansot.com",
    "haodou.com",
    "haoxianglai.com.cn",
    "happycup.ph",
    "happyjoes.com",
    "happyteriyaki.com",
    "hardees.com",
    "hardrockcafe.com",
    "harrisfarm.com.au",
    "hartzchicken.com",
    "harvester.co.uk",
    "harveys.ca",
    "hatcreek.com",
    "hatcreekburger.com",
    "hatcreekburgers.com",
    "havanna.com",
    "havanna.com.br",
    "havmor.com",
    "hawaiianbros.com",
    "heekcaa.com",
    "hefumian.com",
    "heiroku.jp",
    "hellofood.com",
    "hellofood.com.br",
    "hellofood.com.co",
    "hellofood.com.mx",
    "hellofood.com.ng",
    "hellofresh.co.nz",
    "hellofresh.com.au",
    "hellpizza.com",
    "hemkop.se",
    "herfy.com",
    "hesburger.bg",
    "hesburger.com",
    "hesburger.de",
    "hesburger.ee",
    "hesburger.fi",
    "hesburger.lt",
    "hesburger.lv",
    "hesburger.md",
    "hesburger.pl",
    "hesburger.ro",
    "hesburger.ua",
    "heytea.com",
    "hibachisan.com",
    "hidakaya.jp",
    "highnoonrestaurant.com",
    "hipermaxi.com",
    "hippopotamus.fr",
    "hiramatsu.co.jp",
    "hocco.in",
    "hochicken.co.kr",
    "hokulia.com",
    "holiland.com",
    "holiland.com.cn",
    "hollin.cn",
    "hollys.co.kr",
    "homelymeals.in",
    "homeoriginal.com",
    "honbo.com.hk",
    "honestburgers.co.uk",
    "hongkong0410.com",
    "hongkongbanjum.com",
    "honke-sanukiya.co.jp",
    "honmononippon.com",
    "hopdoddy.com",
    "horikawa.jp",
    "hoshino-coffee.com",
    "hosigi.co.kr",
    "hotdogonastick.com",
    "hotelchocolat.com",
    "hotheadburritos.com",
    "hotland.co.jp",
    "houseofpies.com",
    "hsay.com",
    "huaho.com",
    "huangjihuang.com",
    "hubtel.com",
    "huckleberrys.com",
    "huddlehouse.com",
    "hugoapp.co",
    "hugoapp.com",
    "hugodelivery.com",
    "hugodelivery.com.cr",
    "hugodelivery.com.do",
    "hugodelivery.com.gt",
    "hugodelivery.com.hn",
    "hugodelivery.com.jm",
    "hugodelivery.com.ni",
    "hugodelivery.com.pa",
    "hugodelivery.com.sv",
    "hukad.com.ph",
    "hungerstation.com",
    "hungry-panda.com",
    "hungry.ca",
    "hungryhowies.com",
    "hungryhowiespizza.com",
    "hungryhub.com",
    "hungryjacks.com.au",
    "hungrylion.africa",
    "huntbrotherspizza.com",
    "hwy55.com",
    "hwy55burgers.com",
    "hyderabadhouse.com",
    "hyderabadihouse.com",
    "hyodochicken.net",
    "ibaco.in",
    "iberrygroup.com",
    "iberryhomemade.com",
    "ica.se",
    "iceland.co.uk",
    "ichiran.com",
    "ifood.com.br",
    "ifood.com.co",
    "iga.com.au",
    "iheartmacandcheese.com",
    "ihop.ca",
    "iki.lt",
    "ikki.com.tw",
    "ilfornaio.com",
    "illy.com",
    "imdada.cn",
    "immergruen.de",
    "inchcoffee.com",
    "innerchef.com",
    "innout.com",
    "innscorafrica.com",
    "instapizza.in",
    "intermarche.pl",
    "intermarche.pt",
    "ippudo.com",
    "irma.dk",
    "isaactoast.com",
    "islandsrestaurants.com",
    "isomaru.jp",
    "issa.co.jp",
    "isshin-dou.com",
    "itsu.com",
    "izzys.com",
    "jackastors.com",
    "jackinthebox.com",
    "jahez.net",
    "jamba.com",
    "janjijiwa.com",
    "jasonsdeli.com",
    "javahouse.com",
    "javahouseafrica.com",
    "jaya-grocer.com",
    "jd.com",
    "jddj.com",
    "jeremiahsice.com",
    "jeronimoburger.com.br",
    "jeronimomartins.com",
    "jerseymikes.com",
    "jet.dk",
    "jetsamerica.com",
    "jetspizza.com",
    "jimmyjohns.com",
    "jindingxuan.com",
    "jinjin.com.br",
    "jiumaojiu.com",
    "jjbeancoffee.com",
    "jjfishchicken.com",
    "joejuice.com",
    "joescrabshack.com",
    "joeyrestaurants.com",
    "johndorys.com",
    "johnnyrockets.com",
    "johnnyspizza.com",
    "johnnyspizzahouse.com",
    "johnsdrivein.com",
    "jojospizza.com",
    "jollibee.com",
    "jollibee.com.sg",
    "jollibeefoods.com",
    "jonathan.co.jp",
    "joongang.co.kr",
    "jordbaerpikene.no",
    "joyfull.co.jp",
    "jtexpress.com.cn",
    "juanmaestro.cl",
    "juanpollo.com",
    "juanvaldez.com",
    "juanvaldezcafe.com",
    "juiceitup.com",
    "jumbo.cl",
    "jumbo.com",
    "jumboseafood.com.sg",
    "jumia.ci",
    "jumia.co.ke",
    "jumia.ma",
    "jumia.sn",
    "jumiafood.com",
    "juniorkuppanna.com",
    "just-eat.ch",
    "just-eat.co.uk",
    "just-eat.com",
    "just-eat.dk",
    "just-eat.es",
    "just-eat.fr",
    "just-eat.ie",
    "just-eat.it",
    "just-eat.no",
    "justeat.com",
    "justeat.dk",
    "justeat.es",
    "justeat.fr",
    "justeat.it",
    "justeat.no",
    "justeat.se",
    "justo.cl",
    "justo.co",
    "justo.com.ar",
    "justo.com.br",
    "justo.mx",
    "justo.pe",
    "k-ruoka.fi",
    "kabaa.delivery",
    "kabobgrill.com",
    "kabobgrillngo.com",
    "kafelaku.com",
    "kailashparbatgroup.com",
    "kairikiya.co.jp",
    "kaithong.com",
    "kamu-kamu.com",
    "kamukura.co.jp",
    "kappasushi.jp",
    "karachibakery.com",
    "karayama.com",
    "kaspas.co.uk",
    "kathination.com",
    "katinat.vn",
    "katiroll.com",
    "kaufland.de",
    "kcdas.com",
    "kebuke.com",
    "keeta.cn",
    "keeta.com",
    "keeta.hk",
    "keeta.sa",
    "keisuke.co.jp",
    "kelseys.ca",
    "kennysburgerjoint.com",
    "kernels.com",
    "keventers.com",
    "kfc.cl",
    "kfc.co",
    "kfc.co.kr",
    "kfc.co.nz",
    "kfc.co.uk",
    "kfc.com",
    "kfc.com.au",
    "kfc.com.cn",
    "kfc.com.hk",
    "kfc.ke",
    "kfc.pl",
    "kfc.ru",
    "khedmah.app",
    "khudebarta.com",
    "kilimanjaro-restaurants.com",
    "killerburger.com",
    "kimbabcheonguk.co.kr",
    "kimbapnara.co.kr",
    "kindkones.com",
    "kinggyros.com",
    "kingofdonair.ca",
    "kingtaco.com",
    "kitakaro.com",
    "kitakata.co.jp",
    "kiwa-group.co.jp",
    "kiwi.no",
    "kiyoken.com",
    "kkanbu.co.kr",
    "kkanbu.com",
    "klikit.io",
    "kochloeffel.de",
    "koi.com.sg",
    "koicafe.com",
    "koithe.com",
    "komeda-holdings.co.jp",
    "komeda.co.jp",
    "komeda.com.tw",
    "kooul.com",
    "kopikenangan.com",
    "kopitiam.biz",
    "kopps.com",
    "kotipizza.fi",
    "koubei.com",
    "koubei.taobao.com",
    "kourakuen.co.jp",
    "kouryu.co.jp",
    "krispykreme.co.kr",
    "krispykreme.co.uk",
    "krispykreme.com",
    "krispykreme.com.tw",
    "krispykreme.in",
    "krispykreme.jp",
    "krispykrunchy.com",
    "kroshka-kartoshka.ru",
    "krystal.com",
    "kumarakom.com",
    "kunefood.com",
    "kungfu.com.cn",
    "kungfutea.com",
    "kurasushi.tw",
    "kushi-tanaka.com",
    "kuyaj.ph",
    "kwalitywalls.in",
    "kyochon.com",
    "kyubeiya.jp",
    "la-place.com",
    "lacolombe.com",
    "laduree.fr",
    "laemcharoenseafood.com",
    "lagkagehuset.dk",
    "lalamove.com",
    "laobian.com.cn",
    "laoxiangcun.com",
    "laoxiangji.com",
    "lapinozpizza.in",
    "larkburger.com",
    "larosas.com",
    "larosaspizzeria.com",
    "laspalapas.com",
    "laurasecord.ca",
    "lavazza.com",
    "lavazza.com.cn",
    "lavazza.it",
    "lavka.yandex.ru",
    "lawson108.com",
    "lazeezshawarma.com",
    "leeannchin.com",
    "leeschicken.com",
    "leesfamousrecipe.com",
    "leezen.com.tw",
    "lelecha.com",
    "lennys.com",
    "lenta.com",
    "leon.co",
    "leonsfrozencustard.com",
    "lepainquotidien.com",
    "letao.com.tw",
    "letao.jp",
    "licious.in",
    "lider.cl",
    "lidl.co.uk",
    "lidl.de",
    "lieferando.at",
    "lieferando.ch",
    "lieferando.de",
    "liho.com",
    "limefresh.com",
    "limefreshmexicangrill.com",
    "line.me",
    "lineman.co.th",
    "lionchoice.com",
    "lisek.app",
    "liten-easy.com.au",
    "littlebeet.com",
    "littlecaesars.ca",
    "littlecaesars.com",
    "littlegreekfreshgrill.com",
    "littleking.com",
    "liuyishou.com",
    "ljsilvers.com",
    "llaollaoweb.com",
    "localeats.com",
    "logansroadhouse.com",
    "longjohnsilvers.com",
    "longjohnsilvers.com.sg",
    "losbetos.com",
    "loship.vn",
    "losteria.net",
    "lottegrs.com",
    "lotteria.co.kr",
    "lotteria.com",
    "lotteria.jp",
    "lotteria.vn",
    "lotuss.com",
    "louiespizza.com",
    "louiespizzeria.com",
    "louisacoffee.co",
    "louisburger.in",
    "loumalnatis.com",
    "lounges.tv",
    "lucillesbbq.com",
    "luckincoffee.com",
    "luckypierrot.jp",
    "luckywishbone.com",
    "lunchbox.io",
    "m.dianping.com",
    "m.ele.me",
    "macaoimperialtea.com",
    "madforgarlic.com",
    "madgreens.com",
    "madhursweets.in",
    "madmex.com",
    "madoverdonuts.com",
    "maggianos.com",
    "magicpin.in",
    "magnit.ru",
    "magokoro-bento.com",
    "maishoku.com",
    "makro.pl",
    "malan.com.cn",
    "malubianbian.com",
    "mamagoto.com",
    "mamut.cl",
    "manchuwok.com",
    "mandarinoak.com",
    "mandarinrestaurant.com",
    "mandyspizza.com",
    "mangguo.com",
    "manginasal.ph",
    "mangoplate.com",
    "manling.com",
    "manneken.co.jp",
    "mannercoffee.com",
    "mansei.co.jp",
    "marbleslab.ca",
    "marbleslab.com",
    "marche.co.kr",
    "marcos.com",
    "marjane.ma",
    "marleyspoon.com.au",
    "marrybrown.com",
    "marufukucoffeeten.com",
    "marugame-seimen.com",
    "marugame.com",
    "marugen.jp",
    "maruha-net.co.jp",
    "maruichi.co.jp",
    "marukinramen.com",
    "marybrowns.com",
    "marygracecafe.com",
    "masumoto.co.jp",
    "max.dk",
    "max.se",
    "maxburger.com",
    "maxim-asia.com",
    "maxima.ee",
    "maxima.lt",
    "maxima.lv",
    "maximapp.com",
    "maxims.com.hk",
    "maximschinese.com.hk",
    "maxschicken.com",
    "maxsgroupinc.com",
    "mcalistersdeli.com",
    "mccafe.com.cn",
    "mcdelivery.com.hk",
    "mcdonalds.cl",
    "mcdonalds.co.jp",
    "mcdonalds.co.kr",
    "mcdonalds.co.nz",
    "mcdonalds.co.uk",
    "mcdonalds.com",
    "mcdonalds.com.au",
    "mcdonalds.com.br",
    "mcdonalds.com.cn",
    "mcdonalds.com.hk",
    "mcdonalds.com.ph",
    "mcdonalds.com.sg",
    "mcdonalds.com.tw",
    "mcdonalds.eg",
    "mcdonalds.ma",
    "mcdonalds.vn",
    "mcdonaldsindia.com",
    "meals101.com",
    "mealtemple.com",
    "meatheadsburgers.com",
    "mediterraneangrill.com",
    "mega-mgccoffee.com",
    "megamaxi.com",
    "meishi.meituan.com",
    "meishichina.com",
    "meishij.net",
    "meituan.com",
    "meituan.hk",
    "meituan.net",
    "meituanwaimai.com",
    "melcom.com",
    "meltingpot.com",
    "meltshop.com",
    "men-eiji.com",
    "menchies.ca",
    "menchies.com",
    "mendocinofarms.com",
    "menu.ca",
    "menu.jp",
    "menu.ne.jp",
    "menudino.com",
    "menufy.com",
    "menulog.co.nz",
    "menulog.com.au",
    "meny.no",
    "menya-itto.com",
    "menyaitto.com",
    "mercadona.es",
    "merlocoffee.com.au",
    "merqueo.com",
    "metro.pe",
    "mexicaliblues.com",
    "mexicalirose.com",
    "mexicana.co.kr",
    "miescontainer.com",
    "mightytaco.com",
    "mikazuki.co.jp",
    "mikes.ca",
    "mikestavern.com",
    "mikunisushi.com",
    "milestonesrestaurants.com",
    "milkmoo.com.br",
    "milkshoptea.com",
    "miloshamburgers.com",
    "minor.com",
    "minorfood.com",
    "missiontaco.com",
    "mitsuboshi-kaidou.com",
    "mixue.com",
    "mixuebingcheng.com",
    "mjam.net",
    "mkgold.com",
    "mkrestaurant.com",
    "modpizza.com",
    "moes.com",
    "moesoriginalbbq.com",
    "mogumo.jp",
    "mojobar.com",
    "mojocoffee.co.nz",
    "mojopizza.in",
    "momoman.com",
    "momospoint.com",
    "momstouch.co.kr",
    "momstouch.com",
    "monchis.com.py",
    "monginis.net",
    "monogatari.co.jp",
    "monoprix.fr",
    "montana.com.br",
    "montanas.ca",
    "monteroza.co.jp",
    "mooyah.com",
    "morrisons.com",
    "mos.jp",
    "mosburger.co.jp",
    "mosburgerthailand.com",
    "mottu.com.br",
    "moxies.com",
    "mrbeastburger.com",
    "mrbrown.com.tw",
    "mrburger.com",
    "mrdfood.com",
    "mrdfood.com.na",
    "mrhero.com",
    "mrpickles.com",
    "mrpizza.co.kr",
    "mrsool.co",
    "mrsub.ca",
    "mrsub.com",
    "mrwish.com",
    "mryum.com",
    "mstand.cn",
    "muchoburrito.com",
    "mudmanburgers.com",
    "muffinbreak.com.au",
    "munch.africa",
    "mundfein.de",
    "murnidiscovery.com",
    "muruganidlishop.com",
    "muscledeli.jp",
    "mutekiya.com",
    "muteppou.com",
    "mxbc.com",
    "mxj.com.cn",
    "myburgerlab.com",
    "mychef.co.kr",
    "myeongdongtopokki.com",
    "myfood.uz",
    "myfoodbag.co.nz",
    "mynews.com",
    "mypie.com",
    "mypiepizza.com",
    "nafnaf.com",
    "naivas.online",
    "nambafood.kg",
    "namheongipoh.com",
    "nana-coffee.com",
    "nandos.co.uk",
    "nandos.com",
    "nandos.com.au",
    "nantsuttei.com",
    "naplesflatbread.com",
    "napolipizza.jp",
    "napolispizza.com",
    "narvesen.lt",
    "nasilemakshop.com",
    "nationsgianthamburgers.com",
    "nativefoods.com",
    "nativegrillandwings.com",
    "naturalicecreams.in",
    "natureswaycafe.com",
    "nayuki.com",
    "nemlig.com",
    "nenechicken.com",
    "netto.dk",
    "newenglandpizza.com",
    "newks.com",
    "newmaul.com",
    "newworld.co.nz",
    "newyorkfries.com",
    "newyorkpizza.nl",
    "nh1bowls.com",
    "nham24.com",
    "nicicecreams.com",
    "nickthegreek.com",
    "nirulas.com",
    "noblepie.com",
    "noblepieparlor.com",
    "nobrandburger.co.kr",
    "nomadpizza.in",
    "nooa.no",
    "noodlebox.co.kr",
    "noodles.com",
    "norangtongdak.co.kr",
    "nordsee.com",
    "norkys.pe",
    "normspizza.ca",
    "northfish.pl",
    "northitalia.com",
    "northshorepoke.com",
    "nosh.jp",
    "nostrum.eu",
    "nowwa.com",
    "nowwa.com.cn",
    "nypdpizza.com",
    "oakberry.com",
    "oakberry.com.au",
    "oakmaninns.co.uk",
    "oberweis.lu",
    "ochaya.net",
    "oda.com",
    "oddle.me",
    "oishifood.com",
    "oisix.com",
    "okay.be",
    "oldchangkee.com",
    "oldchicago.com",
    "oldschoolburgers.com",
    "oldtown.com",
    "oldwildwest.it",
    "olearys.se",
    "olimpica.com",
    "ondc.org",
    "ondoru.com",
    "onecart.co.za",
    "onesta.in",
    "ontheborder.com",
    "ootoya.com",
    "oporto.com.au",
    "oppadak.co.kr",
    "orangejulius.com",
    "orderahead.com",
    "orderfoodonline.co.za",
    "orderin.co.za",
    "orderinafrica.com",
    "ordernow.ca",
    "orientalkopi.asia",
    "originalchopshop.com",
    "originalhotdogfactory.com",
    "originaljoes.ca",
    "oru.ng",
    "osaka-ohsho.com",
    "osakasushi.com",
    "osmows.com",
    "otlob.com",
    "ottos.com",
    "ourhome.co.kr",
    "outback.co.kr",
    "outback.com",
    "outback.com.br",
    "ovenstory.in",
    "owner.com",
    "pacificcoffee.com",
    "paguemenos.com.br",
    "paikdabang.com",
    "paisanocafe.com",
    "paisanospizza.com",
    "paknsave.co.nz",
    "pal-system.co.jp",
    "pala.com.cn",
    "paliospizza.com",
    "palmbeachgrill.com",
    "palspizza.com",
    "pam.it",
    "panago.com",
    "panarottis.com",
    "pancheros.com",
    "pandaexpress.com",
    "panerabread.com",
    "paninis.com",
    "panos.be",
    "pansandcompany.com",
    "papagallos.com",
    "papajohns.ca",
    "papajohns.cl",
    "papajohns.co.kr",
    "papajohns.co.uk",
    "papajohns.com",
    "papajohns.com.tw",
    "papamurphys.com",
    "papparich.com",
    "paradise-group.com",
    "paradisebakery.com",
    "paradisebiryani.com",
    "paradisefoodcourt.com",
    "paramountfinefoods.com",
    "parathabox.com",
    "pardoschicken.pe",
    "paris.co.kr",
    "parisbaguette.com",
    "parisbaguette.com.cn",
    "parknshop.com",
    "pascucci.co.kr",
    "pastamania.com",
    "pastel-pudding.com",
    "pathao.com",
    "pattyandbun.co.uk",
    "patxispizza.com",
    "paul-uk.com",
    "paul.fr",
    "pedidosonline.com.py",
    "pedidosya.cl",
    "pedidosya.com",
    "pedidosya.com.ar",
    "pedidosya.com.bo",
    "pedidosya.com.cr",
    "pedidosya.com.do",
    "pedidosya.com.ec",
    "pedidosya.com.gt",
    "pedidosya.com.hn",
    "pedidosya.com.ni",
    "pedidosya.com.pa",
    "pedidosya.com.pe",
    "pedidosya.com.py",
    "pedidosya.com.sv",
    "pedidosya.com.uy",
    "pedidosya.pe",
    "pelicana.co.kr",
    "pelicana.com",
    "penn-station.com",
    "pennstation.com",
    "pepesmexican.com",
    "pepperfire.com",
    "pepperjaxgrill.com",
    "pepperlunch.com",
    "peppes.no",
    "perekrestok.ru",
    "perros.com",
    "petesdrivein.com",
    "phillyconnection.com",
    "phoever.co.kr",
    "phohoa.com",
    "picard.fr",
    "pickaroo.com",
    "picklebarrel.ca",
    "picklemans.com",
    "pickndrop.co.ke",
    "pickupcoffee.com",
    "picup.co.za",
    "piefivepizza.com",
    "pieology.com",
    "pieologypizzeria.com",
    "pinchestacos.com",
    "pinchos.se",
    "pindballuchi.com",
    "pinkberryghana.com",
    "pinstripes.com",
    "pitadeli.com",
    "pitagrill.com",
    "pitalite.com",
    "pitapit.ca",
    "pitapit.com",
    "pitapitusa.com",
    "pizza-avanti.de",
    "pizza-max.de",
    "pizza.de",
    "pizza73.com",
    "pizzaalvolo.co.kr",
    "pizzabolis.com",
    "pizzaetang.co.kr",
    "pizzaetang.com",
    "pizzaexpress.com",
    "pizzafactory.com",
    "pizzafactoryinc.com",
    "pizzahut.ca",
    "pizzahut.co.kr",
    "pizzahut.co.nz",
    "pizzahut.co.uk",
    "pizzahut.com",
    "pizzahut.com.au",
    "pizzahut.com.br",
    "pizzahut.com.cn",
    "pizzahut.com.hk",
    "pizzahut.com.ph",
    "pizzahut.com.tw",
    "pizzahut.jp",
    "pizzahut.ma",
    "pizzahut.ng",
    "pizzahut.pl",
    "pizzahut.vn",
    "pizzainn.com",
    "pizzaking.com",
    "pizzaluce.com",
    "pizzamaru.co.kr",
    "pizzamyheart.com",
    "pizzanova.com",
    "pizzapatron.com",
    "pizzapizza.ca",
    "pizzaportal.pl",
    "pizzapro.com",
    "pizzaranch.com",
    "pizzarock.com.tw",
    "pizzaschool.net",
    "pizzastudio.com",
    "pizzaunion.com",
    "pizzaville.ca",
    "planetsmoothie.com",
    "planetsub.com",
    "playmade.com",
    "pluckers.com",
    "plus.nl",
    "pointcoffee.id",
    "pokebar.com",
    "pokebros.com",
    "pokeworks.com",
    "polarbearicecream.com",
    "pollofeliz.com",
    "polloscopacabana.com",
    "pollotropical.com",
    "pompadour.co.jp",
    "ponnusamy.com",
    "popeyes.com",
    "popeyes.vn",
    "popeyesbrasil.com.br",
    "popspizza.com",
    "portillos.com",
    "portilloshotdogs.com",
    "portofsubs.com",
    "postmates.com",
    "potatocorner.com",
    "potbelly.com",
    "potomak.co.jp",
    "presotea.com",
    "pressbyran.se",
    "pret.co.uk",
    "pret.com",
    "pretzelmaker.com",
    "primantibros.com",
    "primoshoagies.com",
    "princepizza.com",
    "prisma.fi",
    "projectpie.com",
    "projectpollo.com",
    "pterrys.com",
    "punjabgrill.in",
    "punthaicoffee.com",
    "puradakchicken.com",
    "purdys.com",
    "puregold.com.ph",
    "putien.com",
    "putien.com.tw",
    "pyszne.pl",
    "qburger.com.tw",
    "qdoba.com",
    "qianlixiang.com",
    "quanjude.com.cn",
    "quesada.ca",
    "quick.be",
    "quick.fr",
    "quick.lu",
    "quickchek.com",
    "quickmart.co.ke",
    "quiznos.co.kr",
    "quiznos.com",
    "rabbitapp.net",
    "rabbitmart.com",
    "radishbo-ya.co.jp",
    "railrestro.com",
    "rainbowdrivein.com",
    "rairaitei.co.jp",
    "raisingcanes.com",
    "rakuten-delivery.com",
    "rallys.com",
    "ramen-jiro.com",
    "ramenhouse.com",
    "ramenizakaya.com",
    "ramennagi.com",
    "ramenya.com",
    "rapidospizza.com",
    "rappi.cl",
    "rappi.co.cr",
    "rappi.com",
    "rappi.com.ar",
    "rappi.com.br",
    "rappi.com.co",
    "rappi.com.mx",
    "rappi.com.uy",
    "rappi.ec",
    "rappi.pe",
    "ratnacafe.com",
    "realgoodjuice.com",
    "realkungfu.com",
    "rebelfoods.com",
    "redburrito.com",
    "redhotandblue.com",
    "redmango.co.kr",
    "redmango.com",
    "redribbon.ph",
    "redribbonbakeshop.com",
    "redrobin.com",
    "redrooster.com.au",
    "reds.ca",
    "redsavoy.com",
    "redsmokebbq.com",
    "redswanpizza.ca",
    "rema.no",
    "rema1000.no",
    "renospizza.com",
    "resto-in.fr",
    "restolib.fr",
    "restomax.fr",
    "restorando.com",
    "restoranrebung.com",
    "rewe.de",
    "ricebox.com",
    "richeesefactory.com",
    "rimi.ee",
    "rimi.lt",
    "rimi.lv",
    "ringerhut.jp",
    "ritasice.com",
    "ritual.co",
    "roastbkk.com",
    "robeks.com",
    "robertscoffee.com",
    "robinhood.in.th",
    "rocketcoffeebar.com",
    "rocketfizz.com",
    "rockychoc.com",
    "rockyrococo.com",
    "rodilla.es",
    "rokkatei.co.jp",
    "rokurinsha.com",
    "rokys.com",
    "rollacosta.com",
    "rollemup.com",
    "rollingpasta.com",
    "rollringpin.com",
    "rolls.fi",
    "rollsking.in",
    "rootsbkk.com",
    "rosatis.com",
    "rosniyom.com",
    "rossopomodoro.it",
    "rostics.ru",
    "rotiboy.com",
    "rotolos.com",
    "roundtable.com",
    "roundtablepizza.com",
    "royal-holdings.co.jp",
    "royalhost.jp",
    "royrogersrestaurants.com",
    "rt-mart.com.tw",
    "rubytuesday.com",
    "runza.com",
    "rushbowls.com",
    "rustica.pe",
    "rustyspizza.com",
    "s-kaupat.fi",
    "saboten.com",
    "saemaeul.com",
    "saemaeul식당.com",
    "sagarratna.in",
    "sainsburys.co.uk",
    "saint-marc-hd.com",
    "saintcinnamon.com",
    "salata.com",
    "salsaritas.com",
    "salspizza.co.nz",
    "saltwatercafe.in",
    "samcheop.com",
    "samokat.ru",
    "sandellas.com",
    "sandwichqbano.com",
    "sangeethaveg.com",
    "sankofoods.com",
    "sanma.com.tw",
    "santaisabel.cl",
    "santouka.co.jp",
    "saravanabhavan.com",
    "sarcletti.com",
    "sarpinos.com",
    "sarutahiko.co",
    "sbarro.com",
    "sbermarket.ru",
    "scarecrow.co.nz",
    "schlotzskys.com",
    "schoolfood.co.kr",
    "scores.ca",
    "scramblers.com",
    "scramblersrestaurants.com",
    "seamless.com",
    "seasidesubs.com",
    "secondcup.com",
    "segafredo.jp",
    "selgros.pl",
    "sendme.ng",
    "sendyit.com",
    "seogaandcook.com",
    "seoudi.com",
    "seoulgarden.com",
    "seoulspice.com",
    "sevenbus.com",
    "sf-express.com",
    "sfbest.com",
    "sfcityrush.com",
    "sfinks.pl",
    "shabushi.com",
    "shahshalalfood.com",
    "shakeshack.com",
    "shakeshack.kr",
    "shakeys.jp",
    "shakeyspizza.ph",
    "shanesribshack.com",
    "shansong.com",
    "sharetea.com",
    "sharetea.com.au",
    "sharis.com",
    "shawarmapalace.ca",
    "shawarmapress.com",
    "shawarmar.com",
    "shaxian.com",
    "sheetz.com",
    "shelbys.ca",
    "shengsiong.com.sg",
    "shidax.co.jp",
    "shinsegaefood.com",
    "shipleydonuts.com",
    "shirokiya.jp",
    "shokutakubin.com",
    "shousi.com.cn",
    "shudaxia.com",
    "shuhada.com",
    "shuijia.com.cn",
    "shuttledelivery.co.kr",
    "shuyi.com",
    "shuyishaoxiancao.com",
    "sibylla.se",
    "silver-life.co.jp",
    "silverdiner.com",
    "silverminesubs.com",
    "simbisa.com",
    "sinimanes.com",
    "sinjeon.co.kr",
    "sixty60.co.za",
    "sizzler.com",
    "skipthedishes.com",
    "skylinechili.com",
    "slapfish.com",
    "slay.coffee",
    "slice.com",
    "slimandhuskys.com",
    "slimchickens.com",
    "smashburger.com",
    "smmarkets.ph",
    "smokeybones.com",
    "smokinjoespizza.com",
    "smoothieking.com",
    "smullers.nl",
    "snappfood.com",
    "snarfburger.com",
    "snoozeeatery.com",
    "snp1344.com",
    "snpfood.com",
    "socialoffline.in",
    "socoffee.pl",
    "somboonseafood.com",
    "sometaro.com",
    "songfa.com.sg",
    "sonicdrivein.com",
    "soupitup.ca",
    "souplantation.com",
    "southstreetburger.com",
    "spangles.com",
    "spanglesinc.com",
    "spar.hu",
    "spar.nl",
    "sparnigeria.com",
    "sphinx.pl",
    "spitz-restaurant.com",
    "spoleto.com.br",
    "sprcoffee.com",
    "spursteakranches.com",
    "st-hubert.com",
    "stacked.com",
    "starbirdchicken.com",
    "starbucks.cl",
    "starbucks.co.jp",
    "starbucks.co.kr",
    "starbucks.co.uk",
    "starbucks.com",
    "starbucks.com.au",
    "starbucks.com.br",
    "starbucks.com.hk",
    "starbucks.in",
    "starbucks.ph",
    "starbucks.pl",
    "stateandmain.ca",
    "steak-ken.com",
    "steakescape.com",
    "steaknshake.com",
    "steiners.com",
    "stickyfingers.com",
    "sto.cn",
    "stokrotka.pl",
    "stonefiregrill.com",
    "stonehotpizza.com",
    "stonehouserestaurants.co.uk",
    "stonemillbread.com",
    "strada-group.jp",
    "subko.coffee",
    "submarina.com",
    "subway.cl",
    "subway.co.jp",
    "subway.co.kr",
    "subway.co.nz",
    "subway.co.uk",
    "subway.com",
    "subway.com.au",
    "subway.com.br",
    "subway.com.sg",
    "subway.com.tw",
    "subway.in",
    "subwayargentina.com",
    "sugakico.co.jp",
    "sugarfire.com",
    "sukiya.jp",
    "sulbing.com",
    "sumireya.com",
    "summershack.com",
    "sunmerry.com.tw",
    "sunset-boulevard.dk",
    "sunsetgrill.ca",
    "sunwaychina.com",
    "superchix.com",
    "supermaxi.com",
    "supernosso.com",
    "supersuper.com.hk",
    "surugaya.co.jp",
    "sushi-mentai.com",
    "sushiblues.cl",
    "sushiclubweb.com",
    "sushiexpress.com.sg",
    "sushiexpress.com.tw",
    "sushihouse.cl",
    "sushimaster.ru",
    "sushipoint.nl",
    "sushiro.co.kr",
    "sushiro.com.sg",
    "sushiro.com.tw",
    "sushitime.nl",
    "sushiwok.ru",
    "sushizanmai.com",
    "sweetandcoffee.com",
    "sweetfrog.com",
    "sweetkiwi.com",
    "sweettomatoes.com",
    "sweettruth.in",
    "swensens.com",
    "swensens.com.sg",
    "swensens1112.com",
    "swensonsdriveins.com",
    "swiggy.com",
    "swisschalet.com",
    "syabuyo.com.tw",
    "symposiumcafe.com",
    "ta.com",
    "tabling.co.kr",
    "tacobell.com",
    "tacobell.com.cn",
    "tacobobs.com",
    "tacobueno.com",
    "tacocabana.com",
    "tacodeli.com",
    "tacojohns.com",
    "tacomacs.com",
    "tacomayo.com",
    "tacomens.com",
    "tacotime.com",
    "tacotimecanada.com",
    "tahinis.com",
    "taier.com",
    "taier.com.cn",
    "taiwanfresh.com.tw",
    "takakuramachi-coffee.co.jp",
    "takarajima.jp",
    "takeaway.com",
    "takeaway.com.be",
    "takomasa.co.jp",
    "takoyaki.co.jp",
    "talabat.com",
    "talabat.com.eg",
    "tamjai-intl.com",
    "tamjaimixian.com",
    "tanameracoffee.com",
    "tanhuoguo.com",
    "tankjuice.co.nz",
    "tanuki.ru",
    "tanyu.com",
    "taobao.com",
    "tapnow.com.my",
    "tasty.com.tw",
    "tastys.com",
    "tazikis.com",
    "tazikiscafe.com",
    "tea-post.com",
    "teabox.com",
    "tealive.asia",
    "teasure.com",
    "teatop.com.tw",
    "teatrails.com",
    "tedsfishfry.com",
    "tedsmontanagrill.com",
    "telepizza.es",
    "telepizza.pl",
    "tenkaippin.co.jp",
    "tenya.co.jp",
    "teppanbaby.com",
    "teremok.ru",
    "teriyakibowl.com",
    "teriyakiboy.com.ph",
    "teriyakiexperience.com",
    "teriyakimadness.com",
    "tesco.com",
    "texaschicken.com",
    "texaschicken.vn",
    "texasroadhouse.com",
    "tezsum.uz",
    "tgif.co.kr",
    "tgifridays.com.tw",
    "thaiexpress.ca",
    "thalappakatti.com",
    "thealley.world",
    "theborn.co.kr",
    "thebreakfastclubcafes.com",
    "thechefz.co",
    "thechickenriceshop.com",
    "thecoffeeclub.com",
    "thecoffeeclub.com.au",
    "thecoffeehouse.com",
    "thegoodbowl.in",
    "thehalalguys.com",
    "thehumanbean.com",
    "themeltingpot.com",
    "theobroma.in",
    "thepizzacompany.com",
    "thepizzacompany.vn",
    "theplace.co.kr",
    "thesimplegreek.com",
    "theventi.co.kr",
    "thewhaletea.com",
    "thincrustpizza.com",
    "thirdwavecoffeeroasters.com",
    "thuisbezorgd.nl",
    "tianlala.com",
    "tibbsfrankie.com",
    "timhortons.co.uk",
    "timhortons.com",
    "timhortonsindia.com",
    "timschina.com",
    "tinysmilkandcookies.com",
    "tkkinc.com.tw",
    "tlj.co.kr",
    "tmall.com",
    "toastbox.com",
    "toastbox.com.sg",
    "toasttab.com",
    "toasttakeout.com",
    "tobycarvery.co.uk",
    "tock.com",
    "tocotocotea.com",
    "tokiya.com.tw",
    "tokmanni.fi",
    "tokyojoes.com",
    "tokyosushiloha.com",
    "tokyoteriyaki.com",
    "tokyotokyo.com.ph",
    "tomandchee.com",
    "tomita-cocoro.jp",
    "tommybeans.cl",
    "tommysburgers.com",
    "tomntoms.com",
    "tongqinglou.com",
    "tonkatsu-aoki.com",
    "tonolucro.com",
    "tonyromas.com",
    "toocle.com",
    "toppers.ca",
    "topperspizza.com",
    "topsdaily.com",
    "torchys.com",
    "torchystacos.com",
    "toreore.com",
    "torikizoku.co.jp",
    "torimero.com",
    "toriton-kita1.jp",
    "tortilla.co.uk",
    "tostao.com",
    "toters.com",
    "totersapp.com",
    "totoyamichi.jp",
    "tottus.cl",
    "toyou.io",
    "tptea.com.tw",
    "travelkhana.com",
    "tripleos.com",
    "tripodking.com.tw",
    "tropicalgrille.com",
    "tropicalsmoothiecafe.com",
    "truedan.com.tw",
    "truffle-bakery.com",
    "trungnguyenlegend.com",
    "trycaviar.com",
    "tsuiwah.com",
    "tsukurioki.jp",
    "tsurumaruudon.com",
    "tsuta79.tokyo",
    "tubbys.com",
    "tullysgoodtimes.com",
    "tupelohoneycafe.com",
    "twistedrootburgerco.com",
    "twosome.co.kr",
    "uber.com",
    "ubereats.com",
    "udon.com",
    "uk.com",
    "unclejohns.ph",
    "unimarc.cl",
    "uno.dz",
    "unos.com",
    "uogashi-nihonichi.com",
    "upa.cl",
    "urbanbricks.com",
    "urbanplates.com",
    "uspizza.in",
    "uspizza.my",
    "uupaotui.com",
    "uupt.com",
    "vadilalicecreams.com",
    "vapiano.com",
    "vegewonder.com",
    "velvettaco.com",
    "vervecoffee.jp",
    "vidaecaffe.com",
    "vidyarthibhavan.in",
    "villa-madina.com",
    "villageburger.com",
    "villageburgerbar.com",
    "villageinn.com",
    "villaitaliankitchen.com",
    "villamarket.com",
    "vintageinn.co.uk",
    "vips.co.kr",
    "vips.es",
    "vitospizza.com",
    "vkusno-i-tochka.ru",
    "vkusvill.ru",
    "volks-steak.jp",
    "vprok.ru",
    "waffleandpancakehouse.com",
    "waffleboy.com.cn",
    "wafflehouse.in",
    "wafflelove.com",
    "wagamama.com",
    "waimai.baidu.com",
    "waimai.meituan.com",
    "waipojia.com",
    "waipojia.com.cn",
    "waitrapp.com",
    "waitrose.com",
    "wako-group.co.jp",
    "walk-ons.com",
    "wallace.com.cn",
    "wangsteak.com.tw",
    "wanpotea.com",
    "warawara.jp",
    "wataburger.in",
    "watami-takushoku.co.jp",
    "watami.co.jp",
    "wavescoffee.com",
    "waweecoffee.com",
    "waybackburgers.com",
    "waynescoffee.se",
    "wedome.com",
    "weiduomei.com",
    "weinerschnitzel.com",
    "wellcome.com.hk",
    "wellcome.com.tw",
    "wellness-dining.com",
    "wendels-bakery.com",
    "wendys-firstkitchen.co.jp",
    "wendys.com",
    "westshorepizza.com",
    "wetzels.com",
    "whataburger.com",
    "whichwich.com",
    "whitecastle.com",
    "whitespot.ca",
    "whyq.sg",
    "wichcraft.com",
    "willys.com",
    "willys.se",
    "wineconnection.com",
    "wingsetc.com",
    "wingsnob.com",
    "wingsnthings.com",
    "wingsover.com",
    "wingstop.co.uk",
    "wingstop.com",
    "wingstop.com.sg",
    "wingzone.com",
    "winmart.vn",
    "wokbox.com",
    "wolt.at",
    "wolt.com",
    "wolt.cz",
    "wolt.de",
    "wolt.ee",
    "wolt.fi",
    "wolt.hr",
    "wolt.jp",
    "wolt.kz",
    "wolt.lt",
    "wolt.lv",
    "wolt.pl",
    "wolt.rs",
    "wong.pe",
    "wongnai.com",
    "woodyspizza.com",
    "woolworths.co.nz",
    "woolworths.com.au",
    "woop.co.nz",
    "woowahan.com",
    "worldofpizza.de",
    "wowbao.com",
    "wowchina.in",
    "wowmomo.com",
    "wowprime.com",
    "wrapcity.com",
    "wufangzhai.com",
    "wuyebanmian.com",
    "xiabu.com",
    "xiachufang.com",
    "xiangcunji.com",
    "xiaofangniu.com",
    "xiaohengshuijiao.com",
    "xiaolongkan.com",
    "xiaonanguo.com",
    "xibei.com",
    "xibei.com.cn",
    "xicha.com",
    "xijiade.com.cn",
    "xingfutang.com",
    "xinladao.com",
    "xsqtea.com",
    "yaekatsu.com",
    "yakiniku-king.jp",
    "yakitoriya.ru",
    "yakiyan.com",
    "yakun.com",
    "yamamotoya.co.jp",
    "yamaokaya.com",
    "yammyfood.kz",
    "yandex.ru",
    "yandexeda.ru",
    "yandexlavka.ru",
    "yangguofu.com",
    "yaposhka.ru",
    "yassir.app",
    "yassir.com",
    "yebofresh.co.za",
    "yellowcabpizza.com",
    "ygfmlt.com",
    "yidiandian.com",
    "yifangtea.com",
    "yihetang.com",
    "yincha.net",
    "yo.co.uk",
    "yogenfruz.com",
    "yogiyo.co.kr",
    "yogurtland.com",
    "yonghe.com.cn",
    "yooco.co.za",
    "yoogane.co.kr",
    "yormas.de",
    "yoshinoya.com",
    "yoshinoyaamerica.com",
    "yosuko.jp",
    "youfoodz.com",
    "yto.net.cn",
    "yudetaro.jp",
    "yumamia.com",
    "yumean.jp",
    "yummy.com.ve",
    "yummy.do",
    "yummycr.com",
    "yumyumtree.com.au",
    "yupdduk.com",
    "yuzuan.jp",
    "zabka.pl",
    "zambrero.com.au",
    "zamp.com.br",
    "zankouchicken.com",
    "zarraffas.com",
    "zax.com",
    "zaxbys.com",
    "zhangliangmalatang.com",
    "zhangliangmlt.com",
    "zhenkungfu.com",
    "zhimeishi.com",
    "zihaiguo.com",
    "zizzi.co.uk",
    "zkungfu.com",
    "zoeskitchen.com",
    "zomato.ae",
    "zomato.com",
    "zoopindia.com",
    "zoup.com",
    "zto.com",
    "zulzi.com",
    "zuotingyouyuan.com",
    "zuscoffee.com",
    "zzgqsh.com"
  ]
}
